internetdownloadmanager/__init__.py
internetdownloadmanager/internetdownloadmanager.py
internetdownloadmanager/utils.py
internetdownloadmanager-0.0.2.dist-info/LICENSE
internetdownloadmanager-0.0.2.dist-info/METADATA
internetdownloadmanager-0.0.2.dist-info/NOTICE
internetdownloadmanager-0.0.2.dist-info/WHEEL
internetdownloadmanager-0.0.2.dist-info/top_level.txt
internetdownloadmanager-0.0.2.dist-info/RECORD
