Metadata-Version: 2.1
Name: internetdownloadmanager
Version: 0.0.2
Summary: file downloader with many requests
Home-page: https://github.com/dinceraslancom/internetdownloadmanager
Author: Dincer Aslan
Author-email: dinceraslan.com@gmail.com
License: UNKNOWN
Project-URL: Source, https://github.com/dinceraslancom/internetdownloadmanager
Platform: UNKNOWN
Classifier: Natural Language :: English
Classifier: License :: OSI Approved :: Apache Software License
Classifier: Programming Language :: Python :: 3
Classifier: Programming Language :: Python :: 3.5
Classifier: Programming Language :: Python :: 3.6
Classifier: Programming Language :: Python :: 3.7
Classifier: Programming Language :: Python :: 3.8
Requires-Python: >=3.0, !=3.0.*, !=3.1.*, !=3.2.*, !=3.3.*, !=3.4.*
Requires-Dist: chardet (<3.1.0,>=3.0.2)
Requires-Dist: idna (<2.9,>=2.5)
Requires-Dist: urllib3 (!=1.25.0,!=1.25.1,<1.26,>=1.21.1)
Requires-Dist: certifi (>=2017.4.17)
Requires-Dist: requests (>=2.22.0)
